LICENSE.txt
MANIFEST.in
README.rst
gorrion.py
pyxtra.py
requirements.txt
screenshot.png
setup.cfg
setup.py
pyxtra.egg-info/PKG-INFO
pyxtra.egg-info/SOURCES.txt
pyxtra.egg-info/dependency_links.txt
pyxtra.egg-info/requires.txt
pyxtra.egg-info/top_level.txt