Metadata-Version: 1.1
Name: pyxtra
Version: 1.6.1
Summary: A small commandline utility to access the Swisscom Xtrazone SMS service
Home-page: https://github.com/dbrgn/pyxtra/
Author: Danilo Bargen, Peter Manser
Author-email: gezuru@gmail.com
License: GPLv3
Keywords: sms,xtrazone,swisscom,communication
Platform: Unix
Platform: Mac
Classifier: Development Status :: 5 - Production/Stable
Classifier: Environment :: Console
Classifier: License :: OSI Approved :: GNU General Public License (GPL)
Classifier: Natural Language :: English
Classifier: Operating System :: MacOS
Classifier: Operating System :: POSIX :: Linux
Classifier: Programming Language :: Python :: 2.5
Classifier: Programming Language :: Python :: 2.6
Classifier: Programming Language :: Python :: 2.7
Classifier: Topic :: Communications
Classifier: Topic :: Internet
Requires: BeautifulSoup
Requires: PIL
Requires: mechanize
Requires: xlrd
Requires: readline
Provides: pyxtra
Provides: gorrion
